{
  "associatedLayout": "Prototype Level 1",
  "name": "UI",
  "instances": [
    {
      "angle": 0,
      "customSize": false,
      "height": 0,
      "layer": "UI",
      "locked": false,
      "name": "HealthTxt",
      "persistentUuid": "4d9e8e09-752b-449f-9573-11efdb682bf6",
      "width": 0,
      "x": 1776,
      "y": 71,
      "zOrder": 8,
      "numberProperties": [],
      "stringProperties": [],
      "initialVariables": []
    },
    {
      "angle": 0,
      "customSize": false,
      "height": 0,
      "layer": "UI",
      "locked": false,
      "name": "StaminaTxt",
      "persistentUuid": "f4ba8350-4b13-487e-993d-c7874adcc967",
      "width": 0,
      "x": 68,
      "y": 64,
      "zOrder": 3,
      "numberProperties": [],
      "stringProperties": [],
      "initialVariables": []
    },
    {
      "angle": 0,
      "customSize": false,
      "height": 0,
      "layer": "UI",
      "locked": false,
      "name": "BubbleCount",
      "persistentUuid": "82925ba9-eebe-40ae-a3f3-7b6a1b3abef4",
      "width": 0,
      "x": 14,
      "y": 14,
      "zOrder": 2,
      "numberProperties": [],
      "stringProperties": [],
      "initialVariables": []
    },
    {
      "angle": 0,
      "customSize": false,
      "height": 0,
      "layer": "UI",
      "locked": false,
      "name": "HealthUI",
      "persistentUuid": "28e559e4-a6cd-49c1-9e1b-c46ffc820d62",
      "width": 0,
      "x": 1562,
      "y": 8,
      "zOrder": 2,
      "numberProperties": [],
      "stringProperties": [],
      "initialVariables": []
    }
  ],
  "editionSettings": {
    "grid": false,
    "gridType": "rectangular",
    "gridWidth": 32,
    "gridHeight": 32,
    "gridOffsetX": 0,
    "gridOffsetY": 0,
    "gridColor": 10401023,
    "gridAlpha": 0.8,
    "snap": false,
    "zoomFactor": 0.3999999999999997,
    "windowMask": false
  }
}